{
  "node_id": "n8n-nodes-base.invoiceNinjaTrigger",
  "name": "Invoice Ninja Trigger",
  "version": 1,
  "semantic_context": "Starts the workflow when Invoice Ninja events occur",
  "natural_language_description": "这是 Invoice Ninja Trigger 节点。主要用于: Starts the workflow when Invoice Ninja events occur",
  "parameters": {
    "apiVersion": {
      "displayName": "API Version",
      "name": "apiVersion",
      "type": "options",
      "required": false,
      "default": "v5",
      "description": "",
      "natural_language_description": "参数名: API Version | 默认值: v5",
      "available_options": [
        "Version 4 (值: v4)",
        "Version 5 (值: v5)"
      ]
    },
    "event": {
      "displayName": "Event",
      "name": "event",
      "type": "options",
      "required": true,
      "default": "",
      "description": "",
      "natural_language_description": "参数名: Event | (必填项)",
      "available_options": [
        "Client Created (值: create_client)",
        "Invoice Created (值: create_invoice)",
        "Payment Created (值: create_payment)",
        "Quote Created (值: create_quote)",
        "Vendor Created (值: create_vendor)"
      ]
    }
  }
}